rank2plan/__init__.py
rank2plan/lp_models/__init__.py
rank2plan/lp_models/constraint_column_generation/__init__.py
rank2plan/lp_models/constraint_column_generation/constraint_column_model.py
rank2plan/lp_models/constraint_column_generation/smoothing_hinge_loss.py
rank2plan/lp_models/constraint_column_generation/utils.py
rank2plan/lp_models/lp_model.py
rank2plan/lp_models/lp_underlying.py
rank2plan/lp_models/objective_values.py
rank2plan/lp_models/primal_lp_model.py
rank2plan/lp_models/utils.py
rank2plan/metrics/__init__.py
rank2plan/metrics/kendall_tau.py
rank2plan/model.py
rank2plan/types.py
rank2plan-0.3.0.dist-info/LICENSE
rank2plan-0.3.0.dist-info/METADATA
rank2plan-0.3.0.dist-info/WHEEL
rank2plan-0.3.0.dist-info/RECORD
