Metadata-Version: 2.1
Name: rank2plan
Version: 0.3.0
Summary: 
Author: Ryan Wang
Author-email: ryanxiaowang2001@gmail.com
Requires-Python: >=3.10,<4.0
Classifier: Programming Language :: Python :: 3
Classifier: Programming Language :: Python :: 3.10
Classifier: Programming Language :: Python :: 3.11
Requires-Dist: bayesian-optimization (>=1.5.1,<2.0.0)
Requires-Dist: numpy (>=1.22.0,<2.0.0)
Requires-Dist: pulp (>=2.8.0,<3.0.0)
Requires-Dist: scipy (>=1.14.1,<2.0.0)
